triggercalib/__init__.py
triggercalib/version.py
triggercalib/crosscheck/__init__.py
triggercalib/crosscheck/factorisation.py
triggercalib/crosscheck/kendall_tau.py
triggercalib/hlteff/__init__.py
triggercalib/hlteff/hlteff.py
triggercalib/objects/__init__.py
triggercalib/objects/fitting.py
triggercalib/objects/plotting.py
triggercalib/objects/sideband.py
triggercalib/tests/__init__.py
triggercalib/tests/conftest.py
triggercalib/tests/crosscheck/__init__.py
triggercalib/tests/crosscheck/conftest.py
triggercalib/tests/crosscheck/test_factorisation_roofit.py
triggercalib/tests/crosscheck/test_factorisation_zfit.py
triggercalib/tests/crosscheck/test_kendall_tau.py
triggercalib/tests/hlteff/__init__.py
triggercalib/tests/hlteff/conftest.py
triggercalib/tests/hlteff/test_fit_count_roofit.py
triggercalib/tests/hlteff/test_fit_count_zfit.py
triggercalib/tests/hlteff/test_raw.py
triggercalib/tests/hlteff/test_sideband.py
triggercalib/tests/hlteff/test_sweights_roofit.py
triggercalib/tests/hlteff/test_sweights_zfit.py
triggercalib/tests/hlteff/test_utils.py
triggercalib/tests/utils/__init__.py
triggercalib/tests/utils/test_helpers.py
triggercalib/tests/utils/test_stats.py
triggercalib/utils/__init__.py
triggercalib/utils/core.py
triggercalib/utils/helpers.py
triggercalib/utils/io.py
triggercalib/utils/stats.py
triggercalib/utils/tests.py
triggercalib/utils/types.py
triggercalib-1.5.2.dist-info/METADATA
triggercalib-1.5.2.dist-info/WHEEL
triggercalib-1.5.2.dist-info/licenses/COPYING
triggercalib-1.5.2.dist-info/RECORD
