Metadata-Version: 2.1
Name: triggercalib
Version: 1.5.2
Summary: A turnkey package for estimating LHCb trigger efficiencies
Project-URL: Homepage, https://gitlab.cern.ch/lhcb-rta/triggercalib/
Project-URL: Documentation, https://triggercalib.docs.cern.ch/
Project-URL: Bug Tracker, https://gitlab.cern.ch/lhcb-rta/triggercalib/-/issues
Author-email: Jamie Gooding <jamie.gooding@cern.ch>
License-File: COPYING
Keywords: efficiencies,lhcb,tistos,trigger
Requires-Python: >=3.6
Requires-Dist: hepstats
Requires-Dist: lhcbstyle
Requires-Dist: numpy
Requires-Dist: sweights
Provides-Extra: zfit
Requires-Dist: tensorflow==2.16.1; extra == 'zfit'
Requires-Dist: zfit==0.23.0; extra == 'zfit'
